Metadata-Version: 1.0
Name: stadist
Version: 0.1
Summary: Gaussian and Binomial distributions
Home-page: UNKNOWN
Author: Lucas Pontes
Author-email: lucas.pontesm@gmail.com
License: UNKNOWN
Platform: UNKNOWN
